modlamp/__init__.py
modlamp/analysis.py
modlamp/core.py
modlamp/database.py
modlamp/datasets.py
modlamp/descriptors.py
modlamp/ml.py
modlamp/plot.py
modlamp/sequences.py
modlamp/version.py
modlamp/wetlab.py
modlamp/data/ACP_CancPPD_vs_Random.csv
modlamp/data/ACP_CancPPD_vs_TM.csv
modlamp/data/AMPvsTMset.csv
modlamp/data/AMPvsUniProt.csv
modlamp/data/custom.csv
modlamp/data/test.fasta
modlamp-4.3.2.data/scripts/example_descriptors.py
modlamp-4.3.2.data/scripts/example_modlamp.py
modlamp-4.3.2.dist-info/LICENSE
modlamp-4.3.2.dist-info/METADATA
modlamp-4.3.2.dist-info/WHEEL
modlamp-4.3.2.dist-info/top_level.txt
modlamp-4.3.2.dist-info/RECORD
