Metadata-Version: 2.1
Name: modlamp
Version: 4.3.2
Summary: python package for in silico peptide design and QSAR studies
Home-page: http://modlamp.org
Author: Alex Müller, Gisela Gabernet
Author-email: alexarnimueller@protonmail.com
License: BSD-3
Keywords: antimicrobial anticancer peptide descriptor sequences QSAR machine learning design
Platform: UNKNOWN
Classifier: Development Status :: 5 - Production/Stable
Classifier: Intended Audience :: Science/Research
Classifier: Topic :: Scientific/Engineering :: Bio-Informatics
Classifier: Topic :: Scientific/Engineering :: Chemistry
Classifier: Topic :: Scientific/Engineering :: Medical Science Apps.
Classifier: License :: OSI Approved :: BSD License
Classifier: Programming Language :: Python :: 3
Classifier: Programming Language :: Python :: 3.6
License-File: LICENSE
Requires-Dist: setuptools (>=20.2.2)
Requires-Dist: nose (>=1.3.7)
Requires-Dist: numpy (>=1.10.4)
Requires-Dist: scipy (>=0.17.0)
Requires-Dist: matplotlib (>=1.5.1)
Requires-Dist: scikit-learn (>=0.18.0)
Requires-Dist: pandas (>=0.18.1)
Requires-Dist: requests (>=2.11.1)
Requires-Dist: lxml (>=3.6.4)
Requires-Dist: joblib (>=0.15.1)
Requires-Dist: mysql-connector-python (>=8.0)
